LICENSE.txt
MANIFEST.in
README.txt
pep8.txt
setup.py
scunch/__init__.py
scunch/_tools.py
scunch/antglob.py
scunch/scunch.py
scunch/test_antglob.py
scunch/test_scunch.py
scunch/test_tools.py
scunch.egg-info/PKG-INFO
scunch.egg-info/SOURCES.txt
scunch.egg-info/dependency_links.txt
scunch.egg-info/entry_points.txt
scunch.egg-info/requires.txt
scunch.egg-info/top_level.txt