Metadata-Version: 1.1
Name: scunch
Version: 0.5.8
Summary: Update svn working copy from folder.
Home-page: http://pypi.python.org/pypi/scunch/
Author: Thomas Aglassinger
Author-email: roskakori@users.sourceforge.net
License: GNU Library or Lesser General Public License (LGPL)
Keywords: svn scm version import apply copy transfer punch working work
Platform: UNKNOWN
Classifier: Development Status :: 3 - Alpha
Classifier: Environment :: Console
Classifier: Intended Audience :: Developers
Classifier: Intended Audience :: System Administrators
Classifier: License :: OSI Approved :: GNU Library or Lesser General Public License (LGPL)
Classifier: Natural Language :: English
Classifier: Operating System :: OS Independent
Classifier: Programming Language :: Python :: 2.6
Classifier: Programming Language :: Python :: 2.7
Classifier: Topic :: Software Development :: Version Control
